pycsgogpt/__init__.py
pycsgogpt/__main__.py
pycsgogpt/csgo_chatbot.py
pycsgogpt-0.1.6.dist-info/LICENSE
pycsgogpt-0.1.6.dist-info/METADATA
pycsgogpt-0.1.6.dist-info/WHEEL
pycsgogpt-0.1.6.dist-info/entry_points.txt
pycsgogpt-0.1.6.dist-info/RECORD
