Metadata-Version: 2.1
Name: pycsgogpt
Version: 0.1.6
Summary: CSGO Chatbot using OpenAI GPT-3.5 Turbo.
Home-page: https://github.com/nikeix/pycsgogpt
License: MIT
Keywords: csgo,chatbot,openai,gpt
Author: Aviv
Author-email: 4440524+nikeix@users.noreply.github.com
Requires-Python: >=3.7.1,<4.0.0
Classifier: License :: OSI Approved :: MIT License
Classifier: Programming Language :: Python :: 3
Classifier: Programming Language :: Python :: 3.8
Classifier: Programming Language :: Python :: 3.9
Classifier: Programming Language :: Python :: 3.10
Classifier: Programming Language :: Python :: 3.11
Classifier: Programming Language :: Python :: 3.7
Requires-Dist: backoff (>=2.2.1,<3.0.0)
Requires-Dist: openai (>=0.27.8,<0.28.0)
Requires-Dist: telnetlib3 (>=2.0.2,<3.0.0)
Requires-Dist: typer (>=0.9.0,<0.10.0)
Project-URL: Repository, https://github.com/nikeix/pycsgogpt
